LICENSE
MANIFEST.in
README.md
pybeautifier.py
setup.py
pybeautifier.egg-info/PKG-INFO
pybeautifier.egg-info/SOURCES.txt
pybeautifier.egg-info/dependency_links.txt
pybeautifier.egg-info/entry_points.txt
pybeautifier.egg-info/requires.txt
pybeautifier.egg-info/top_level.txt