Metadata-Version: 2.1
Name: pybeautifier
Version: 0.1.3
Summary: Python beautifier tcp server
Home-page: https://github.com/guyskk/pybeautifier
Author: guyskk
Author-email: guyskk@qq.com
License: MIT
Keywords: beautifier autopep8 yapf isort
Platform: UNKNOWN
Classifier: Development Status :: 4 - Beta
Classifier: Intended Audience :: Developers
Classifier: Topic :: Software Development :: Build Tools
Classifier: License :: OSI Approved :: MIT License
Classifier: Programming Language :: Python :: 3
Classifier: Operating System :: POSIX
